{
    "021": {
        "UserID": "M30",
        "Readings": {
            "000000": {
                "Phase": "baseline 021 M30",
                "Time": "19:24:37",
                "Engagement": "0.60951",
                "Excitement": "0.29496",
                "Stress": "0.36712",
                "Relaxation": "0.38944",
                "Interest": "0.45368",
                "Focus": "0.37092"
            },
            "000001": {
                "Phase": "baseline 021 M30",
                "Time": "19:24:47",
                "Engagement": "0.71769",
                "Excitement": "0.34564",
                "Stress": "0.34736",
                "Relaxation": "0.43056",
                "Interest": "0.5082",
                "Focus": "0.50808"
            },
            "000002": {
                "Phase": "baseline 021 M30",
                "Time": "19:24:57",
                "Engagement": "0.66855",
                "Excitement": "0.32609",
                "Stress": "0.33985",
                "Relaxation": "0.33182",
                "Interest": "0.46186",
                "Focus": "0.41359"
            },
            "000003": {
                "Phase": "baseline 021 M30",
                "Time": "19:25:07",
                "Engagement": "0.57176",
                "Excitement": "0.67132",
                "Stress": "0.30933",
                "Relaxation": "0.3047",
                "Interest": "0.42779",
                "Focus": "0.38223"
            },
            "000004": {
                "Phase": "baseline 021 M30",
                "Time": "19:25:17",
                "Engagement": "0.55921",
                "Excitement": "0.70706",
                "Stress": "0.33854",
                "Relaxation": "0.34523",
                "Interest": "0.43989",
                "Focus": "0.31171"
            },
            "000005": {
                "Phase": "baseline 021 M30",
                "Time": "19:25:27",
                "Engagement": "0.5962",
                "Excitement": "0.50819",
                "Stress": "0.32925",
                "Relaxation": "0.33757",
                "Interest": "0.51449",
                "Focus": "0.44887"
            },
            "000006": {
                "Phase": "baseline 021 M30",
                "Time": "19:25:37",
                "Engagement": "0.44703",
                "Excitement": "0.22391",
                "Stress": "0.30686",
                "Relaxation": "0.28071",
                "Interest": "0.40952",
                "Focus": "0.22064"
            },
            "000007": {
                "Phase": "baseline 021 M30",
                "Time": "19:25:47",
                "Engagement": "0.34471",
                "Excitement": "0.13196",
                "Stress": "0.31355",
                "Relaxation": "0.29623",
                "Interest": "0.4013",
                "Focus": "0.10547"
            },
            "000008": {
                "Phase": "baseline 021 M30",
                "Time": "19:25:57",
                "Engagement": "0.37053",
                "Excitement": "0.15562",
                "Stress": "0.3804",
                "Relaxation": "0.34471",
                "Interest": "0.39516",
                "Focus": "0.14963"
            },
            "000009": {
                "Phase": "baseline 021 M30",
                "Time": "19:26:07",
                "Engagement": "0.42509",
                "Excitement": "0.15538",
                "Stress": "0.32179",
                "Relaxation": "0.30173",
                "Interest": "0.3984",
                "Focus": "0.14985"
            },
            "000010": {
                "Phase": "baseline 021 M30",
                "Time": "19:26:17",
                "Engagement": "0.33828",
                "Excitement": "0.1805",
                "Stress": "0.33666",
                "Relaxation": "0.30968",
                "Interest": "0.39763",
                "Focus": "0.17342"
            },
            "000011": {
                "Phase": "baseline 021 M30",
                "Time": "19:26:27",
                "Engagement": "0.35469",
                "Excitement": "0.15143",
                "Stress": "0.31429",
                "Relaxation": "0.24316",
                "Interest": "0.36681",
                "Focus": "0.17325"
            },
            "000012": {
                "Phase": "baseline 021 M30",
                "Time": "19:26:37",
                "Engagement": "0.40337",
                "Excitement": "0.14087",
                "Stress": "0.31015",
                "Relaxation": "0.30083",
                "Interest": "0.38718",
                "Focus": "0.10169"
            },
            "000013": {
                "Phase": "baseline 021 M30",
                "Time": "19:26:47",
                "Engagement": "0.29689",
                "Excitement": "0.14914",
                "Stress": "0.30842",
                "Relaxation": "0.30167",
                "Interest": "0.40679",
                "Focus": "0.12015"
            },
            "000014": {
                "Phase": "baseline 021 M30",
                "Time": "19:26:57",
                "Engagement": "0.37682",
                "Excitement": "0.25039",
                "Stress": "0.31664",
                "Relaxation": "0.26144",
                "Interest": "0.3949",
                "Focus": "0.19055"
            },
            "000015": {
                "Phase": "baseline 021 M30",
                "Time": "19:27:07",
                "Engagement": "0.21519",
                "Excitement": "0.1995",
                "Stress": "0.31952",
                "Relaxation": "0.35201",
                "Interest": "0.43954",
                "Focus": "0.06733"
            },
            "000016": {
                "Phase": "baseline 021 M30",
                "Time": "19:27:17",
                "Engagement": "0.34136",
                "Excitement": "0.24666",
                "Stress": "0.29157",
                "Relaxation": "0.2298",
                "Interest": "0.37585",
                "Focus": "0.12766"
            },
            "000017": {
                "Phase": "baseline 021 M30",
                "Time": "19:27:27",
                "Engagement": "0.35599",
                "Excitement": "0.74318",
                "Stress": "0.26955",
                "Relaxation": "0.22407",
                "Interest": "0.37101",
                "Focus": "0.10177"
            },
            "000018": {
                "Phase": "baseline 021 M30",
                "Time": "19:27:37",
                "Engagement": "0.21888",
                "Excitement": "0.74349",
                "Stress": "0.3116",
                "Relaxation": "0.33164",
                "Interest": "0.42954",
                "Focus": "0.08442"
            },
            "000019": {
                "Phase": "baseline occhi chiusi",
                "Time": "19:28:07",
                "Engagement": "0.1755",
                "Excitement": "0.57591",
                "Stress": "0.3674",
                "Relaxation": "0.38229",
                "Interest": "0.43339",
                "Focus": "0.09691"
            },
            "000020": {
                "Phase": "baseline occhi chiusi",
                "Time": "19:28:17",
                "Engagement": "0.13818",
                "Excitement": "0.25999",
                "Stress": "0.30508",
                "Relaxation": "0.30459",
                "Interest": "0.41522",
                "Focus": "0.06664"
            },
            "000021": {
                "Phase": "baseline occhi chiusi",
                "Time": "19:28:27",
                "Engagement": "0.10957",
                "Excitement": "0.17194",
                "Stress": "0.33391",
                "Relaxation": "0.34648",
                "Interest": "0.40864",
                "Focus": "0.06458"
            },
            "000022": {
                "Phase": "baseline occhi chiusi",
                "Time": "19:28:37",
                "Engagement": "0.11886",
                "Excitement": "0.22325",
                "Stress": "0.31361",
                "Relaxation": "0.31757",
                "Interest": "0.41202",
                "Focus": "0.06294"
            },
            "000023": {
                "Phase": "baseline occhi chiusi",
                "Time": "19:28:47",
                "Engagement": "0.0683",
                "Excitement": "0.7357",
                "Stress": "0.28474",
                "Relaxation": "0.29206",
                "Interest": "0.42367",
                "Focus": "0.05012"
            },
            "000024": {
                "Phase": "baseline occhi chiusi",
                "Time": "19:28:57",
                "Engagement": "0.05173",
                "Excitement": "0.75193",
                "Stress": "0.29424",
                "Relaxation": "0.28042",
                "Interest": "0.42255",
                "Focus": "0.04198"
            },
            "000025": {
                "Phase": "baseline occhi chiusi",
                "Time": "19:29:07",
                "Engagement": "0.12287",
                "Excitement": "0.63405",
                "Stress": "0.31188",
                "Relaxation": "0.33922",
                "Interest": "0.43083",
                "Focus": "0.05486"
            },
            "000026": {
                "Phase": "baseline occhi chiusi",
                "Time": "19:29:17",
                "Engagement": "0.16399",
                "Excitement": "0.41964",
                "Stress": "0.30807",
                "Relaxation": "0.35103",
                "Interest": "0.42564",
                "Focus": "0.06577"
            },
            "000027": {
                "Phase": "baseline occhi chiusi",
                "Time": "19:29:27",
                "Engagement": "0.12895",
                "Excitement": "0.25856",
                "Stress": "0.27512",
                "Relaxation": "0.28307",
                "Interest": "0.41245",
                "Focus": "0.05363"
            },
            "000028": {
                "Phase": "baseline occhi chiusi",
                "Time": "19:29:37",
                "Engagement": "0.15083",
                "Excitement": "0.13943",
                "Stress": "0.27891",
                "Relaxation": "0.2423",
                "Interest": "0.39136",
                "Focus": "0.07004"
            },
            "000029": {
                "Phase": "baseline occhi chiusi",
                "Time": "19:29:47",
                "Engagement": "0.14946",
                "Excitement": "0.15",
                "Stress": "0.29499",
                "Relaxation": "0.29698",
                "Interest": "0.42142",
                "Focus": "0.09179"
            },
            "000030": {
                "Phase": "baseline occhi chiusi",
                "Time": "19:29:57",
                "Engagement": "0.12787",
                "Excitement": "0.13986",
                "Stress": "0.30341",
                "Relaxation": "0.32594",
                "Interest": "0.42244",
                "Focus": "0.04074"
            },
            "000031": {
                "Phase": "baseline occhi chiusi",
                "Time": "19:30:07",
                "Engagement": "0.09555",
                "Excitement": "0.11839",
                "Stress": "0.30832",
                "Relaxation": "0.35206",
                "Interest": "0.42776",
                "Focus": "0.04853"
            },
            "000032": {
                "Phase": "baseline occhi chiusi",
                "Time": "19:30:17",
                "Engagement": "0.14834",
                "Excitement": "0.12012",
                "Stress": "0.33919",
                "Relaxation": "0.35322",
                "Interest": "0.43058",
                "Focus": "0.0601"
            },
            "000033": {
                "Phase": "baseline occhi chiusi",
                "Time": "19:30:27",
                "Engagement": "0.08985",
                "Excitement": "0.12449",
                "Stress": "0.27667",
                "Relaxation": "0.31602",
                "Interest": "0.43059",
                "Focus": "0.05201"
            },
            "000034": {
                "Phase": "baseline occhi chiusi",
                "Time": "19:30:37",
                "Engagement": "0.12536",
                "Excitement": "0.12347",
                "Stress": "0.31557",
                "Relaxation": "0.35796",
                "Interest": "0.43954",
                "Focus": "0.06157"
            },
            "000035": {
                "Phase": "baseline occhi chiusi",
                "Time": "19:30:47",
                "Engagement": "0.09329",
                "Excitement": "0.14939",
                "Stress": "0.29219",
                "Relaxation": "0.33668",
                "Interest": "0.44698",
                "Focus": "0.05182"
            },
            "000036": {
                "Phase": "baseline occhi chiusi",
                "Time": "19:30:57",
                "Engagement": "0.0893",
                "Excitement": "0.16668",
                "Stress": "0.29612",
                "Relaxation": "0.35854",
                "Interest": "0.44602",
                "Focus": "0.04295"
            },
            "000037": {
                "Phase": "baseline occhi chiusi",
                "Time": "19:31:07",
                "Engagement": "0.09416",
                "Excitement": "0.22958",
                "Stress": "0.26489",
                "Relaxation": "0.29769",
                "Interest": "0.44409",
                "Focus": "0.04369"
            },
            "000038": {
                "Phase": "baseline occhi chiusi",
                "Time": "19:31:17",
                "Engagement": "0.16031",
                "Excitement": "0.14645",
                "Stress": "0.27393",
                "Relaxation": "0.29411",
                "Interest": "0.43933",
                "Focus": "0.07312"
            },
            "000039": {
                "Phase": "baseline occhi chiusi",
                "Time": "19:31:27",
                "Engagement": "0.1644",
                "Excitement": "0.21267",
                "Stress": "0.31174",
                "Relaxation": "0.32343",
                "Interest": "0.43206",
                "Focus": "0.0742"
            },
            "000040": {
                "Phase": "baseline occhi chiusi",
                "Time": "19:31:37",
                "Engagement": "0.08403",
                "Excitement": "0.16228",
                "Stress": "0.23894",
                "Relaxation": "0.25166",
                "Interest": "0.43252",
                "Focus": "0.05682"
            },
            "000041": {
                "Phase": "Macchinine 1",
                "Time": "19:33:37",
                "Engagement": "0.53912",
                "Excitement": "0.44174",
                "Stress": "0.34251",
                "Relaxation": "0.33249",
                "Interest": "0.45229",
                "Focus": "0.43394"
            },
            "000042": {
                "Phase": "Macchinine 1",
                "Time": "19:33:47",
                "Engagement": "0.59609",
                "Excitement": "0.58339",
                "Stress": "0.35454",
                "Relaxation": "0.40262",
                "Interest": "0.47849",
                "Focus": "0.47685"
            },
            "000043": {
                "Phase": "Macchinine 1",
                "Time": "19:33:57",
                "Engagement": "0.60597",
                "Excitement": "0.48811",
                "Stress": "0.35344",
                "Relaxation": "0.389",
                "Interest": "0.46331",
                "Focus": "0.4829"
            },
            "000044": {
                "Phase": "Macchinine 1",
                "Time": "19:34:07",
                "Engagement": "0.6588",
                "Excitement": "0.65948",
                "Stress": "0.35938",
                "Relaxation": "0.39538",
                "Interest": "0.47887",
                "Focus": "0.57678"
            },
            "000045": {
                "Phase": "Macchinine 1",
                "Time": "19:34:17",
                "Engagement": "0.67222",
                "Excitement": "0.68419",
                "Stress": "0.36712",
                "Relaxation": "0.40051",
                "Interest": "0.48315",
                "Focus": "0.55359"
            },
            "000046": {
                "Phase": "Macchinine 1",
                "Time": "19:34:27",
                "Engagement": "0.67035",
                "Excitement": "0.75075",
                "Stress": "0.33988",
                "Relaxation": "0.3735",
                "Interest": "0.48036",
                "Focus": "0.48539"
            },
            "000047": {
                "Phase": "Macchinine 1",
                "Time": "19:34:37",
                "Engagement": "0.67985",
                "Excitement": "0.54709",
                "Stress": "0.3221",
                "Relaxation": "0.33488",
                "Interest": "0.45125",
                "Focus": "0.50285"
            },
            "000048": {
                "Phase": "Macchinine 1",
                "Time": "19:34:47",
                "Engagement": "0.62852",
                "Excitement": "0.25909",
                "Stress": "0.30762",
                "Relaxation": "0.27342",
                "Interest": "0.42766",
                "Focus": "0.4097"
            },
            "000049": {
                "Phase": "Macchinine 1",
                "Time": "19:34:57",
                "Engagement": "0.62821",
                "Excitement": "0.16888",
                "Stress": "0.33837",
                "Relaxation": "0.35972",
                "Interest": "0.44494",
                "Focus": "0.38615"
            },
            "000050": {
                "Phase": "Macchinine 1",
                "Time": "19:35:07",
                "Engagement": "0.65051",
                "Excitement": "0.19814",
                "Stress": "0.36259",
                "Relaxation": "0.34398",
                "Interest": "0.44127",
                "Focus": "0.47243"
            },
            "000051": {
                "Phase": "Macchinine 1",
                "Time": "19:35:17",
                "Engagement": "0.67022",
                "Excitement": "0.29784",
                "Stress": "0.37332",
                "Relaxation": "0.36415",
                "Interest": "0.45375",
                "Focus": "0.53801"
            },
            "000052": {
                "Phase": "Macchinine 1",
                "Time": "19:35:27",
                "Engagement": "0.62272",
                "Excitement": "0.65285",
                "Stress": "0.36934",
                "Relaxation": "0.34961",
                "Interest": "0.42873",
                "Focus": "0.44709"
            },
            "000053": {
                "Phase": "Macchinine 1",
                "Time": "19:35:37",
                "Engagement": "0.55583",
                "Excitement": "0.41518",
                "Stress": "0.35315",
                "Relaxation": "0.31399",
                "Interest": "0.41919",
                "Focus": "0.38861"
            },
            "000054": {
                "Phase": "Macchinine 1",
                "Time": "19:35:47",
                "Engagement": "0.57301",
                "Excitement": "0.28503",
                "Stress": "0.34698",
                "Relaxation": "0.32195",
                "Interest": "0.42781",
                "Focus": "0.32344"
            },
            "000055": {
                "Phase": "Macchinine 1",
                "Time": "19:35:57",
                "Engagement": "0.58456",
                "Excitement": "0.61821",
                "Stress": "0.36533",
                "Relaxation": "0.3211",
                "Interest": "0.41493",
                "Focus": "0.37599"
            },
            "000056": {
                "Phase": "Macchinine 1",
                "Time": "19:36:08",
                "Engagement": "0.56562",
                "Excitement": "0.6487",
                "Stress": "0.32488",
                "Relaxation": "0.29577",
                "Interest": "0.41885",
                "Focus": "0.35149"
            },
            "000057": {
                "Phase": "Macchinine 1",
                "Time": "19:36:18",
                "Engagement": "0.68658",
                "Excitement": "0.61311",
                "Stress": "0.41778",
                "Relaxation": "0.50771",
                "Interest": "0.52085",
                "Focus": "0.49401"
            },
            "000058": {
                "Phase": "Macchinine 1",
                "Time": "19:36:27",
                "Engagement": "0.68684",
                "Excitement": "0.51477",
                "Stress": "0.39038",
                "Relaxation": "0.4388",
                "Interest": "0.50159",
                "Focus": "0.54393"
            },
            "000059": {
                "Phase": "Macchinine 1",
                "Time": "19:36:37",
                "Engagement": "0.68797",
                "Excitement": "0.64621",
                "Stress": "0.36915",
                "Relaxation": "0.428",
                "Interest": "0.50503",
                "Focus": "0.51806"
            },
            "000060": {
                "Phase": "sudoku",
                "Time": "19:39:08",
                "Engagement": "0.41416",
                "Excitement": "0.13622",
                "Stress": "0.31297",
                "Relaxation": "0.27788",
                "Interest": "0.51889",
                "Focus": "0.20198"
            },
            "000061": {
                "Phase": "sudoku",
                "Time": "19:39:18",
                "Engagement": "0.43577",
                "Excitement": "0.12228",
                "Stress": "0.28877",
                "Relaxation": "0.24089",
                "Interest": "0.43795",
                "Focus": "0.26424"
            },
            "000062": {
                "Phase": "sudoku",
                "Time": "19:39:28",
                "Engagement": "0.42082",
                "Excitement": "0.11904",
                "Stress": "0.27245",
                "Relaxation": "0.22992",
                "Interest": "0.4288",
                "Focus": "0.21894"
            },
            "000063": {
                "Phase": "sudoku",
                "Time": "19:39:38",
                "Engagement": "0.40052",
                "Excitement": "0.13803",
                "Stress": "0.29758",
                "Relaxation": "0.25061",
                "Interest": "0.45394",
                "Focus": "0.20181"
            },
            "000064": {
                "Phase": "sudoku",
                "Time": "19:39:48",
                "Engagement": "0.43651",
                "Excitement": "0.11881",
                "Stress": "0.32094",
                "Relaxation": "0.24512",
                "Interest": "0.43997",
                "Focus": "0.22687"
            },
            "000065": {
                "Phase": "sudoku",
                "Time": "19:39:58",
                "Engagement": "0.40787",
                "Excitement": "0.12105",
                "Stress": "0.32712",
                "Relaxation": "0.28297",
                "Interest": "0.45074",
                "Focus": "0.20735"
            },
            "000066": {
                "Phase": "sudoku",
                "Time": "19:40:08",
                "Engagement": "0.4097",
                "Excitement": "0.12073",
                "Stress": "0.29023",
                "Relaxation": "0.25008",
                "Interest": "0.44811",
                "Focus": "0.18013"
            },
            "000067": {
                "Phase": "sudoku",
                "Time": "19:40:18",
                "Engagement": "0.42607",
                "Excitement": "0.12537",
                "Stress": "0.30556",
                "Relaxation": "0.2752",
                "Interest": "0.42157",
                "Focus": "0.1714"
            },
            "000068": {
                "Phase": "sudoku",
                "Time": "19:40:28",
                "Engagement": "0.44757",
                "Excitement": "0.14114",
                "Stress": "0.32027",
                "Relaxation": "0.30851",
                "Interest": "0.49628",
                "Focus": "0.21172"
            },
            "000069": {
                "Phase": "sudoku",
                "Time": "19:40:38",
                "Engagement": "0.40953",
                "Excitement": "0.14899",
                "Stress": "0.36799",
                "Relaxation": "0.37719",
                "Interest": "0.53102",
                "Focus": "0.21409"
            },
            "000070": {
                "Phase": "sudoku",
                "Time": "19:40:48",
                "Engagement": "0.41667",
                "Excitement": "0.14548",
                "Stress": "0.29081",
                "Relaxation": "0.23068",
                "Interest": "0.43063",
                "Focus": "0.21738"
            },
            "000071": {
                "Phase": "sudoku",
                "Time": "19:40:58",
                "Engagement": "0.44483",
                "Excitement": "0.13686",
                "Stress": "0.31487",
                "Relaxation": "0.28461",
                "Interest": "0.44078",
                "Focus": "0.22163"
            },
            "000072": {
                "Phase": "sudoku",
                "Time": "19:41:08",
                "Engagement": "0.42007",
                "Excitement": "0.14508",
                "Stress": "0.33645",
                "Relaxation": "0.30202",
                "Interest": "0.43896",
                "Focus": "0.19715"
            },
            "000073": {
                "Phase": "sudoku",
                "Time": "19:41:18",
                "Engagement": "0.48838",
                "Excitement": "0.16432",
                "Stress": "0.32672",
                "Relaxation": "0.30039",
                "Interest": "0.4534",
                "Focus": "0.2144"
            },
            "000074": {
                "Phase": "sudoku",
                "Time": "19:41:28",
                "Engagement": "0.45002",
                "Excitement": "0.20582",
                "Stress": "0.33825",
                "Relaxation": "0.31418",
                "Interest": "0.43253",
                "Focus": "0.23445"
            },
            "000075": {
                "Phase": "sudoku",
                "Time": "19:41:38",
                "Engagement": "0.45163",
                "Excitement": "0.14891",
                "Stress": "0.31621",
                "Relaxation": "0.30242",
                "Interest": "0.41497",
                "Focus": "0.22063"
            },
            "000076": {
                "Phase": "sudoku",
                "Time": "19:41:48",
                "Engagement": "0.46718",
                "Excitement": "0.14229",
                "Stress": "0.279",
                "Relaxation": "0.22006",
                "Interest": "0.39826",
                "Focus": "0.23009"
            },
            "000077": {
                "Phase": "sudoku",
                "Time": "19:41:58",
                "Engagement": "0.43681",
                "Excitement": "0.14468",
                "Stress": "0.28691",
                "Relaxation": "0.23381",
                "Interest": "0.41252",
                "Focus": "0.21619"
            },
            "000078": {
                "Phase": "macchinine 2",
                "Time": "19:42:58",
                "Engagement": "0.33829",
                "Excitement": "0.14617",
                "Stress": "0.30528",
                "Relaxation": "0.26235",
                "Interest": "0.39586",
                "Focus": "0.15571"
            },
            "000079": {
                "Phase": "macchinine 2",
                "Time": "19:43:08",
                "Engagement": "0.46647",
                "Excitement": "0.13845",
                "Stress": "0.29867",
                "Relaxation": "0.23899",
                "Interest": "0.39563",
                "Focus": "0.22399"
            },
            "000080": {
                "Phase": "macchinine 2",
                "Time": "19:43:18",
                "Engagement": "0.54251",
                "Excitement": "0.25512",
                "Stress": "0.35604",
                "Relaxation": "0.3284",
                "Interest": "0.45713",
                "Focus": "0.37274"
            },
            "000081": {
                "Phase": "macchinine 2",
                "Time": "19:43:28",
                "Engagement": "0.58591",
                "Excitement": "0.35743",
                "Stress": "0.348",
                "Relaxation": "0.31571",
                "Interest": "0.44848",
                "Focus": "0.37588"
            },
            "000082": {
                "Phase": "macchinine 2",
                "Time": "19:43:38",
                "Engagement": "0.59261",
                "Excitement": "0.20044",
                "Stress": "0.35233",
                "Relaxation": "0.32886",
                "Interest": "0.4331",
                "Focus": "0.35806"
            },
            "000083": {
                "Phase": "macchinine 2",
                "Time": "19:43:48",
                "Engagement": "0.56694",
                "Excitement": "0.27502",
                "Stress": "0.35813",
                "Relaxation": "0.35679",
                "Interest": "0.45343",
                "Focus": "0.34386"
            },
            "000084": {
                "Phase": "macchinine 2",
                "Time": "19:43:58",
                "Engagement": "0.56261",
                "Excitement": "0.28946",
                "Stress": "0.31794",
                "Relaxation": "0.26467",
                "Interest": "0.41422",
                "Focus": "0.2995"
            },
            "000085": {
                "Phase": "macchinine 2",
                "Time": "19:44:08",
                "Engagement": "0.52511",
                "Excitement": "0.14121",
                "Stress": "0.30059",
                "Relaxation": "0.25215",
                "Interest": "0.40759",
                "Focus": "0.22996"
            },
            "000086": {
                "Phase": "macchinine 2",
                "Time": "19:44:18",
                "Engagement": "0.47474",
                "Excitement": "0.14989",
                "Stress": "0.342",
                "Relaxation": "0.29241",
                "Interest": "0.42668",
                "Focus": "0.27241"
            },
            "000087": {
                "Phase": "macchinine 2",
                "Time": "19:44:28",
                "Engagement": "0.50968",
                "Excitement": "0.14975",
                "Stress": "0.32537",
                "Relaxation": "0.2625",
                "Interest": "0.41243",
                "Focus": "0.32665"
            },
            "000088": {
                "Phase": "macchinine 2",
                "Time": "19:44:38",
                "Engagement": "0.49423",
                "Excitement": "0.15738",
                "Stress": "0.30675",
                "Relaxation": "0.23331",
                "Interest": "0.38799",
                "Focus": "0.29684"
            },
            "000089": {
                "Phase": "macchinine 2",
                "Time": "19:44:48",
                "Engagement": "0.49782",
                "Excitement": "0.17622",
                "Stress": "0.28922",
                "Relaxation": "0.19735",
                "Interest": "0.38055",
                "Focus": "0.28864"
            },
            "000090": {
                "Phase": "macchinine 2",
                "Time": "19:44:58",
                "Engagement": "0.53349",
                "Excitement": "0.26536",
                "Stress": "0.3835",
                "Relaxation": "0.40117",
                "Interest": "0.43339",
                "Focus": "0.29549"
            },
            "000091": {
                "Phase": "macchinine 2",
                "Time": "19:45:08",
                "Engagement": "0.44083",
                "Excitement": "0.24144",
                "Stress": "0.31496",
                "Relaxation": "0.25917",
                "Interest": "0.39402",
                "Focus": "0.25493"
            },
            "000092": {
                "Phase": "macchinine 2",
                "Time": "19:45:18",
                "Engagement": "0.50543",
                "Excitement": "0.25914",
                "Stress": "0.27885",
                "Relaxation": "0.21687",
                "Interest": "0.38272",
                "Focus": "0.28129"
            },
            "000093": {
                "Phase": "macchinine 2",
                "Time": "19:45:28",
                "Engagement": "0.50833",
                "Excitement": "0.26009",
                "Stress": "0.29324",
                "Relaxation": "0.27462",
                "Interest": "0.40061",
                "Focus": "0.20233"
            },
            "000094": {
                "Phase": "macchinine 2",
                "Time": "19:45:38",
                "Engagement": "0.47231",
                "Excitement": "0.29396",
                "Stress": "0.29804",
                "Relaxation": "0.25265",
                "Interest": "0.39437",
                "Focus": "0.2512"
            },
            "000095": {
                "Phase": "macchinine 2",
                "Time": "19:45:48",
                "Engagement": "0.50262",
                "Excitement": "0.33768",
                "Stress": "0.2982",
                "Relaxation": "0.26786",
                "Interest": "0.41254",
                "Focus": "0.28279"
            },
            "000096": {
                "Phase": "macchinine 2",
                "Time": "19:45:58",
                "Engagement": "0.51306",
                "Excitement": "0.33329",
                "Stress": "0.30271",
                "Relaxation": "0.25832",
                "Interest": "0.40069",
                "Focus": "0.25064"
            },
            "000097": {
                "Phase": "macchinine 2",
                "Time": "19:46:08",
                "Engagement": "0.49392",
                "Excitement": "0.31485",
                "Stress": "0.27489",
                "Relaxation": "0.24811",
                "Interest": "0.40515",
                "Focus": "0.21846"
            }
        }
    }
}